fario/__about__.py
fario/__init__.py
fario/config.py
fario/debug.py
fario/fario.py
fario/fario2json.py
fario/fario_account.py
fario/fario_backup.py
fario/fario_cast.py
fario/fario_fid_byname.py
fario/fario_grep.py
fario/fario_hub_info.py
fario/fario_in.py
fario/fario_out.py
fario/fario_pprint.py
fario/fario_signers.py
fario/fario_userdata.py
fario/json2fario.py
fario/textcast.py
fario-0.7.14.dist-info/METADATA
fario-0.7.14.dist-info/WHEEL
fario-0.7.14.dist-info/entry_points.txt
fario-0.7.14.dist-info/licenses/LICENSE
fario-0.7.14.dist-info/RECORD
