Metadata-Version: 2.3
Name: fario
Version: 0.7.14
Project-URL: Documentation, https://github.com/vrypan/fario
Project-URL: Source, https://github.com/vrypan/fario
License-Expression: MIT
License-File: LICENSE
Keywords: farcaster
Requires-Dist: blake3
Requires-Dist: click
Requires-Dist: farcaster-py>=0.1.4
Requires-Dist: pynacl
Requires-Dist: python-dotenv
